{
  "name": "Sara Webb",
  "age": 58,
  "address": {
    "street": "Awizu View",
    "city": "Wisukvo",
    "state": "SC",
    "zip": "48859"
  },
  "contact": {
    "phone": "(605) 541-9568",
    "servicePhone": "800128837"
  },
  "birthday": "2001-11-25T07:29:21.272Z",
  "ip": "176.145.25.82",
  "foo": "bar",
  "profile": {
    "about": "Ta famji pad tig jubas jigowvar favtav ahiruk afpir jo omvulej nuhpiaku wa rizehaw. Afsuh tajib jojefwa fac umo hi rujkos targefuv ovetazkuk tiga tim ubo lo kov zalmidez. Vowula hek mowjappis epe noukte vopmicu lokaeku lozuco noten bavute kaut jobgu fefrosgej tugicafod okrajos calin. Dukugi hipi ofji jam vife leswoac za gi bamceciso za giprino paz sa de cikoftu met bi ki. Mepukgi wus egsu efu cebo sirol cucodti ditfut kek aza uj sogha ogaasnis tuc. Ma dovjow bor pu paehoku poj hir erotur ej vuvukku fem roli wo pewo vemjikas zo fec.",
    "bio": "Mihadres ew famuzo hok obihegte onuva le sup ta ra ciarfo wovew ivzif bal. Em ket ugrikbu ezre vojtucew poosi copwur viwpiv gaz fumroj uhi pov. Ekezet cicerupo muffon kaiski du alsulve ocuotoim wethehik kegoto lumugem jesuf ot ada itubege lo ikjijla."
  },
  "apiKey": "bdc74545f9989e39074ff4da1e3f6b740d329214663a667ca872f50a0e6abb05",
  "currency": {
    "code": "CHF",
    "name": "Switzerland Franc"
  }
}