{
  "name": "Brandon Rowe",
  "age": 31,
  "address": {
    "street": "Jafliv Circle",
    "city": "Holzarzab",
    "state": "WA",
    "zip": "56086"
  },
  "contact": {
    "phone": "(252) 498-9522",
    "servicePhone": "800536478"
  },
  "birthday": "1974-11-27T02:41:05.039Z",
  "ip": "134.14.18.87",
  "foo": "bar",
  "profile": {
    "about": "Reklir ihezi upreled difabzu kakedwe neweleb ohteg wahma kot tonhugum mobemgag seuk regobe befbav wiliabu gilpi hu. Ni kaj dalhoacu guiwerec livi pumtag ziwu ifo sod fa ruhe moj. Iga penzase re li cociiz woredu he divhuj du bum lumvaod vopge ribi rawiw arinewu zifazre. Nabnu zewa izga bo damsuk pithuja kivre kug hoc loretodid icupiz kap luvte zego ikewuw otujis mo zovif.",
    "bio": "Bubelafun hegweug tevsut detjovuw oreed kejezpe oboflo zuf azinak ocfo faw eco ku ek mah sedga ub didal. Vuc enu lurimu rugul man wasitwo to giveg apohif cob feakwak wirur dunusob po. Pota ziplitu ru bakosnic hunova naugi kojsa somajga lujehinol ehdo repvovab kakajju vesoj se hej."
  },
  "apiKey": "bc8e68faa8d9a81df6e6ad8c600710b35556fbfb7c3df32e6c6b65c2ba2484d4",
  "currency": {
    "code": "BBD",
    "name": "Barbados Dollar"
  }
}