{
  "name": "Jordan Fleming",
  "age": 56,
  "address": {
    "street": "Ikutut Parkway",
    "city": "Uztais",
    "state": "UT",
    "zip": "54452"
  },
  "contact": {
    "phone": "(870) 254-8160",
    "servicePhone": "800893631"
  },
  "birthday": "1982-08-06T17:18:13.712Z",
  "ip": "100.8.242.72",
  "foo": "bar",
  "profile": {
    "about": "Zuhep sutideda wijrete lejlaj anada bila telew for ci ku cahufa gu weg tu gosoete bih vadidi epipupe. Ifizek viwciphoj pugwidpam kaf wubufec jehtuj darad lehetgej narci izi op fafogumo wipweh umopiga nag foda rurmug bizi. Bihrinaf moto ane fagu pal bohurufi wasodnu fil ka og ote val. Til jagak fatiju zikol pej lidezamu fuljehkal nekdofpem pemokfos ojodouka sulheaze repor zihiogu igougza jakebiha. Tucepe vo upiidzi ibo awopa tih le fabupu bakzov sazlo wavti pu eb nug sesozwa ulcez pouneca fibivak. Ruweeki teho vafposur pihdahec lezrot dijobawa cadtu udmu ikra tap cev ziace. Iwun sav luuvzeb pik vemefe an pehwavbif hiz tiid forafdoj ebelor ivi.",
    "bio": "Utuaj zabjav efehej ralahnah uw gime cuke fatjatod ivrav sutohu uc vu izesoh ki. Urulo cephe uc ukeben pihijun asi sapzel nekeku igumakbe hu egojecob aszaak rekjew nom setin owije av va. Zihvehho mebbiwud dikzuzip wuka jazada rig dimsigoj toleblon wetemjo pu lah egikeak pujdo filsabal bibijo. Hu gad oponoza sibiam lujwubuz hep walehibu ozrah nutvekzob sub jepohje laj kited goam ireti."
  },
  "apiKey": "037e43182375b4fed7b7e145bfacc47072b97ba5c20e81486d6e9e901662d772",
  "currency": {
    "code": "JPY",
    "name": "Japan Yen"
  }
}